message_store/__about__.py
message_store/__init__.py
message_store/message.py
message_store/message_from_subscription.py
message_store/message_metadata.py
message_store/message_store.py
message_store/message_store_logger.py
message_store/retry_with_exponential_backoff.py
message_store/timeout_exception.py
message_store/projections/fetch.py
message_store/projections/projection.py
message_store/subscriptions/progress_reporter.py
message_store/subscriptions/subscription.py
message_store-0.3.0.dist-info/METADATA
message_store-0.3.0.dist-info/WHEEL
message_store-0.3.0.dist-info/licenses/LICENSE
message_store-0.3.0.dist-info/RECORD
