Metadata-Version: 2.3
Name: message-store
Version: 0.3.0
Summary: Message Store is an event sourcing implementation on top of NATS JetStream
Project-URL: Documentation, https://github.com/zencastr/message-store#readme
Project-URL: Issues, https://github.com/zencastr/message-store
Project-URL: Source, https://github.com/zencastr/message-store
Author-email: Rui Figueiredo <rui@zencastr.com>, Alex Cannan <alex@zencastr.com>, Volodymyr Kyrylov <volodymyr@zencastr.com>
License-Expression: MIT
License-File: LICENSE
Classifier: Development Status :: 4 - Beta
Classifier: Framework :: AsyncIO
Classifier: Intended Audience :: Developers
Classifier: License :: OSI Approved :: MIT License
Classifier: Natural Language :: English
Classifier: Operating System :: OS Independent
Classifier: Programming Language :: Python
Classifier: Programming Language :: Python :: 3.10
Classifier: Programming Language :: Python :: 3.11
Classifier: Programming Language :: Python :: Implementation :: CPython
Classifier: Topic :: Communications
Classifier: Topic :: Software Development :: Libraries :: Python Modules
Requires-Python: >=3.10
Requires-Dist: nats-py[nkeys]
